xh/__init__.py
xh/core.py
xh/py.typed
xhell-0.2.1.dist-info/LICENSE
xhell-0.2.1.dist-info/METADATA
xhell-0.2.1.dist-info/WHEEL
xhell-0.2.1.dist-info/RECORD
