Metadata-Version: 2.3
Name: xhell
Version: 0.2.1
Summary: Shell library for Windows and Wrapper for sh for Linux and MacOS
License: BSD 3 Clause
Author: Ivan Ogasawara
Author-email: ivan.ogasawara@gmail.com
Requires-Python: >=3.9,<4
Classifier: License :: Other/Proprietary License
Classifier: Programming Language :: Python :: 3
Classifier: Programming Language :: Python :: 3.9
Classifier: Programming Language :: Python :: 3.10
Classifier: Programming Language :: Python :: 3.11
Classifier: Programming Language :: Python :: 3.12
Classifier: Programming Language :: Python :: 3.13
Requires-Dist: sh (>=2) ; platform_system != "Windows"
